pythoncircle/__init__.py
pythoncircle/circle.py
pythoncircle-1.0.dist-info/LICENSE
pythoncircle-1.0.dist-info/METADATA
pythoncircle-1.0.dist-info/WHEEL
pythoncircle-1.0.dist-info/top_level.txt
pythoncircle-1.0.dist-info/RECORD
