Metadata-Version: 2.1
Name: pythoncircle
Version: 1.0
Summary: function that returns the area
Author: Dimuthu M
Author-email: dtperera.dp@gmail.com
License: MIT
Platform: UNKNOWN
License-File: LICENSE
